{
  "app": {
    "[project]/src/app/_not-found/page": [
      "static/media/0acc7fdf55eb3220-s.p.12o-f1.6qra-s.woff2",
      "static/media/c9bd7381a27f2960-s.p.0nt9ayxdmqydo.woff2"
    ],
    "[project]/src/app/anu/page": [
      "static/media/0acc7fdf55eb3220-s.p.12o-f1.6qra-s.woff2",
      "static/media/c9bd7381a27f2960-s.p.0nt9ayxdmqydo.woff2"
    ],
    "[project]/src/app/kirastudios/dysunsrealm/dysunsark/page": [
      "static/media/0acc7fdf55eb3220-s.p.12o-f1.6qra-s.woff2",
      "static/media/c9bd7381a27f2960-s.p.0nt9ayxdmqydo.woff2"
    ],
    "[project]/src/app/kirastudios/dysunsrealm/page": [
      "static/media/0acc7fdf55eb3220-s.p.12o-f1.6qra-s.woff2",
      "static/media/c9bd7381a27f2960-s.p.0nt9ayxdmqydo.woff2"
    ],
    "[project]/src/app/kirastudios/frostheim/page": [
      "static/media/0acc7fdf55eb3220-s.p.12o-f1.6qra-s.woff2",
      "static/media/c9bd7381a27f2960-s.p.0nt9ayxdmqydo.woff2"
    ],
    "[project]/src/app/kirastudios/namtar/namtarark/page": [
      "static/media/0acc7fdf55eb3220-s.p.12o-f1.6qra-s.woff2",
      "static/media/c9bd7381a27f2960-s.p.0nt9ayxdmqydo.woff2"
    ],
    "[project]/src/app/kirastudios/namtar/page": [
      "static/media/0acc7fdf55eb3220-s.p.12o-f1.6qra-s.woff2",
      "static/media/c9bd7381a27f2960-s.p.0nt9ayxdmqydo.woff2"
    ],
    "[project]/src/app/kirastudios/page": [
      "static/media/0acc7fdf55eb3220-s.p.12o-f1.6qra-s.woff2",
      "static/media/c9bd7381a27f2960-s.p.0nt9ayxdmqydo.woff2"
    ],
    "[project]/src/app/kyrax/page": [
      "static/media/0acc7fdf55eb3220-s.p.12o-f1.6qra-s.woff2",
      "static/media/c9bd7381a27f2960-s.p.0nt9ayxdmqydo.woff2"
    ],
    "[project]/src/app/namtarsurvey/page": [
      "static/media/0acc7fdf55eb3220-s.p.12o-f1.6qra-s.woff2",
      "static/media/c9bd7381a27f2960-s.p.0nt9ayxdmqydo.woff2"
    ],
    "[project]/src/app/page": [
      "static/media/0acc7fdf55eb3220-s.p.12o-f1.6qra-s.woff2",
      "static/media/c9bd7381a27f2960-s.p.0nt9ayxdmqydo.woff2"
    ],
    "[project]/src/app/pulse/page": [
      "static/media/0acc7fdf55eb3220-s.p.12o-f1.6qra-s.woff2",
      "static/media/c9bd7381a27f2960-s.p.0nt9ayxdmqydo.woff2"
    ]
  },
  "appUsingSizeAdjust": true,
  "pages": {},
  "pagesUsingSizeAdjust": false
}